tensorrec/__init__.py
tensorrec/errors.py
tensorrec/eval.py
tensorrec/input_utils.py
tensorrec/loss_graphs.py
tensorrec/prediction_graphs.py
tensorrec/recommendation_graphs.py
tensorrec/representation_graphs.py
tensorrec/session_management.py
tensorrec/tensorrec.py
tensorrec/util.py
tensorrec-0.26.2.dist-info/LICENSE
tensorrec-0.26.2.dist-info/METADATA
tensorrec-0.26.2.dist-info/WHEEL
tensorrec-0.26.2.dist-info/top_level.txt
tensorrec-0.26.2.dist-info/RECORD
