Metadata-Version: 2.1
Name: tensorrec
Version: 0.26.2
Summary: A TensorFlow recommendation algorithm and framework in Python.
Home-page: https://github.com/jfkirk/tensorrec
Author: James Kirk
Author-email: james.f.kirk@gmail.com
License: UNKNOWN
Keywords: machine-learning,tensorflow,recommendation-system,python,recommender-system
Platform: UNKNOWN
Requires-Dist: numpy (>=1.14.1)
Requires-Dist: scipy (>=0.19.1)
Requires-Dist: six (==1.11.0)
Requires-Dist: tensorflow (>=1.7.0)
